redmine2jira/__init__.py
redmine2jira/cli.py
redmine2jira/config.py
redmine2jira/redmine2jira.py
redmine2jira/exporters/__init__.py
redmine2jira/exporters/issues.py
redmine2jira/resources/__init__.py
redmine2jira/resources/mappings.py
redmine2jira/resources/models.py
redmine2jira/utils/__init__.py
redmine2jira/utils/text.py
redmine2jira-0.10.0.dist-info/DESCRIPTION.rst
redmine2jira-0.10.0.dist-info/METADATA
redmine2jira-0.10.0.dist-info/RECORD
redmine2jira-0.10.0.dist-info/WHEEL
redmine2jira-0.10.0.dist-info/entry_points.txt
redmine2jira-0.10.0.dist-info/metadata.json
redmine2jira-0.10.0.dist-info/top_level.txt
