Metadata-Version: 2.0
Name: redmine2jira
Version: 0.10.0
Summary: Export Redmine issues to file formats compatible with the JIRA Importers plugin (JIM) 
Home-page: https://github.com/wandering-tales/redmine2jira
Author: Michele Cardone
Author-email: michele.cardone82@gmail.com
License: MIT license
Keywords: redmine2jira
Platform: UNKNOWN
Classifier: Development Status :: 2 - Pre-Alpha
Classifier: Intended Audience :: Developers
Classifier: License :: OSI Approved :: MIT License
Classifier: Natural Language :: English
Classifier: Programming Language :: Python :: 2
Classifier: Programming Language :: Python :: 2.7
Classifier: Programming Language :: Python :: 3
Classifier: Programming Language :: Python :: 3.4
Classifier: Programming Language :: Python :: 3.5
Classifier: Programming Language :: Python :: 3.6
Requires-Dist: Click (>=6.0)
Requires-Dist: click-default-group (>=1.2)
Requires-Dist: contextlib2 (==0.5.5)
Requires-Dist: future (>=0.16.0)
Requires-Dist: inflection (>=0.3)
Requires-Dist: isodate (>=0.6)
Requires-Dist: lxml (>=4.1)
Requires-Dist: markdown (>=2.6)
Requires-Dist: Pillow (>=5.0)
Requires-Dist: python-redmine (<2.1,>=2.0)
Requires-Dist: regex (>=2018.2)
Requires-Dist: six (>=1.11)
Requires-Dist: tabulate (>=0.8)
Requires-Dist: textile (>=3.0)
